{
	"$schema": "https://json.schemastore.org/block.json",
	"apiVersion": 2,
	"name": "oese-block/oese-disruptive-content-block",
	"version": "0.1.0",
	"title": "Disruptive Content",
	"category": "oese-block-category",
	"icon": "media-document",
	"description": "Add disruptive content block",
	"supports": {
		"html": false
	},
	"attributes":{
    "blockid": {"type":"string"}
  },
	"textdomain": "oese-disruptive-content-block",
	"editorScript": "file:./build/index.js",
	"editorStyle": "file:./build/index.css",
	"style": "file:./build/style-index.css"
}